LICENSE
README.md
openpo/__init__.py
openpo/client.py
openpo/internal/__init__.py
openpo/internal/error.py
openpo/internal/helper.py
openpo/internal/prompt.py
openpo/internal/response.py
openpo/resources/__init__.py
openpo/resources/batch/__init__.py
openpo/resources/batch/batch.py
openpo/resources/completion/__init__.py
openpo/resources/completion/completion.py
openpo/resources/eval/__init__.py
openpo/resources/eval/eval.py
openpo/resources/pairrm/__init__.py
openpo/resources/pairrm/pairrm.py
openpo/resources/prometheus2/__init__.py
openpo/resources/prometheus2/prometheus2.py
openpo/resources/prometheus2/vllm.py
openpo/resources/provider/__init__.py
openpo/resources/provider/anthropic.py
openpo/resources/provider/base.py
openpo/resources/provider/huggingface.py
openpo/resources/provider/openai.py
openpo/resources/provider/openrouter.py
openpo/resources/provider/vllm.py
openpo/storage/__init__.py
openpo/storage/huggingface.py
openpo/storage/s3.py
openpo-0.7.7.dist-info/LICENSE
openpo-0.7.7.dist-info/METADATA
openpo-0.7.7.dist-info/WHEEL
openpo-0.7.7.dist-info/RECORD
