Metadata-Version: 2.1
Name: openpo
Version: 0.7.7
Summary: Build high quality synthetic datasets with AI feedback from 200+ LLMs
Home-page: https://github.com/dannylee1020/openpo
License: Apache-2.0
Keywords: llm,finetuning,ai,rlaif,preference tuning,synthetic data generation,synthetic data
Author: Daniel Lee
Author-email: dannylee1020@gmail.com
Requires-Python: >=3.10.1,<4.0
Classifier: License :: OSI Approved :: Apache Software License
Classifier: Programming Language :: Python :: 3
Classifier: Programming Language :: Python :: 3.11
Classifier: Programming Language :: Python :: 3.12
Provides-Extra: eval
Provides-Extra: vllm
Requires-Dist: anthropic (>=0.40.0,<0.41.0)
Requires-Dist: boto3 (>=1.35.57,<2.0.0)
Requires-Dist: datasets (>=3.1.0,<4.0.0)
Requires-Dist: httpx (>=0.27.2,<0.28.0)
Requires-Dist: huggingface-hub (>=0.26.2,<0.27.0)
Requires-Dist: llm-blender (>=0.0.2,<0.0.3) ; extra == "eval"
Requires-Dist: numpy (>=1.26.4,<2.0.0)
Requires-Dist: openai (>=1.57.1,<2.0.0)
Requires-Dist: pandas (>=2.2.3,<3.0.0)
Requires-Dist: prometheus-eval (>=0.1.20,<0.2.0) ; extra == "eval"
Requires-Dist: pydantic (>=2.9.2,<3.0.0)
Requires-Dist: triton (==3.1.0) ; extra == "eval" or extra == "vllm"
Requires-Dist: vllm (>=0.6.4.post1,<0.7.0) ; extra == "eval" or extra == "vllm"
Project-URL: Documentation, https://docs.openpo.dev
Project-URL: Repository, https://github.com/dannylee1020/openpo
